plot2gltf/__init__.py
plot2gltf/fonts/DejaVuSerif.ttf
plot2gltf-1.0.7.dist-info/WHEEL
plot2gltf-1.0.7.dist-info/METADATA
plot2gltf-1.0.7.dist-info/RECORD
