Metadata-Version: 2.3
Name: plot2gltf
Version: 1.0.7
Summary: A module for creating GLTF files with various geometric primitives and 3D text labels.
Author-email: Yotam Gingold <yotam@yotamgingold.com>
Classifier: License :: CC0 1.0 Universal (CC0 1.0) Public Domain Dedication
Requires-Dist: numpy>=2.0.0
Requires-Dist: pillow>=11.0.0
Requires-Dist: pygltflib>=1.16.2
Project-URL: Home, https://github.com/yig/plot2gltf
